README.md
setup.cfg
setup.py
inex_nats_bridge_client.egg-info/PKG-INFO
inex_nats_bridge_client.egg-info/SOURCES.txt
inex_nats_bridge_client.egg-info/dependency_links.txt
inex_nats_bridge_client.egg-info/requires.txt
inex_nats_bridge_client.egg-info/top_level.txt
nats_bridge_client/__init__.py
nats_bridge_client/client.py