Metadata-Version: 2.1
Name: inex-nats-bridge-client
Version: 1.0.0
Summary: DMZ-LAN NATS bridge client
Home-page: UNKNOWN
Author-email: dev.viten.center@gmail.com
License: UNKNOWN
Keywords: inex
Platform: UNKNOWN
Classifier: Intended Audience :: Developers
Classifier: Topic :: Software Development :: Build Tools
Classifier: Programming Language :: Python :: 3.6
Classifier: Programming Language :: Python :: 3.7
Classifier: Programming Language :: Python :: 3.8
Requires-Python: >=3.6, <4
Provides-Extra: dev
